setup.py
wiki_helper/__init__.py
wiki_helper/main.py
wiki_helper.egg-info/PKG-INFO
wiki_helper.egg-info/SOURCES.txt
wiki_helper.egg-info/dependency_links.txt
wiki_helper.egg-info/not-zip-safe
wiki_helper.egg-info/requires.txt
wiki_helper.egg-info/top_level.txt