Metadata-Version: 1.0
Name: wiki-helper
Version: 0.1.3
Summary: Helpers for extracting some data from Wikipedia
Home-page: https://bitbucket.org/amist/wiki_helper
Author: Amitay Stern
Author-email: stern.amitay@gmail.com
License: MIT
Platform: UNKNOWN
